grampa/__init__.py
grampa/__version.py
grampa/magneticfieldmodel.py
grampa/magneticfieldmodel_old.py
grampa/magneticfieldmodel_utils.py
grampa-0.0.7.dist-info/METADATA
grampa-0.0.7.dist-info/WHEEL
grampa-0.0.7.dist-info/licenses/LICENSE
grampa-0.0.7.dist-info/RECORD
