Metadata-Version: 2.4
Name: grampa
Version: 0.0.7
Summary: Gaussian Random-fields Approximation for Magnetic-fields with Python Algorithms (GRAMPA)
Project-URL: Homepage, https://github.com/ErikOsinga/grampa
Author-email: Erik Osinga <erik.osinga@utoronto.ca>
License: MIT License
License-File: LICENSE
Classifier: Operating System :: OS Independent
Classifier: Programming Language :: Python :: 3
Requires-Python: >=3.8
Requires-Dist: astropy
Requires-Dist: matplotlib
Requires-Dist: numpy
Requires-Dist: psutil
Requires-Dist: pyfc
Requires-Dist: pyfftw
Requires-Dist: scikit-image
Requires-Dist: scipy
Provides-Extra: dev
Requires-Dist: furo; extra == 'dev'
Requires-Dist: isort; extra == 'dev'
Requires-Dist: mypy; extra == 'dev'
Requires-Dist: myst-parser; extra == 'dev'
Requires-Dist: pre-commit; extra == 'dev'
Requires-Dist: pytest; extra == 'dev'
Requires-Dist: pytest-cov; extra == 'dev'
Requires-Dist: pytest-rerunfailures; extra == 'dev'
Requires-Dist: pytest-xdist; extra == 'dev'
Requires-Dist: ruff; extra == 'dev'
Requires-Dist: sphinx; extra == 'dev'
Requires-Dist: sphinx-argparse; extra == 'dev'
Requires-Dist: sphinx-autoapi; extra == 'dev'
Requires-Dist: sphinx-autodoc-typehints; extra == 'dev'
Requires-Dist: sphinx-copybutton; extra == 'dev'
